tests/test_extension.py
tests/conftest.py
tests/test_connect.py
tests/util.py
tests/__init__.py
tests/dummy_server.py
tests/test_binary_map.py
tests/test_ssl.py
tests/test_partition_awareness.py
tests/ssl/client.pem
tests/ssl/ca.pem
tests/ssl/client_unknown.pem
pygridgain-9.1.16.dist-info/RECORD
pygridgain-9.1.16.dist-info/WHEEL
pygridgain-9.1.16.dist-info/top_level.txt
pygridgain-9.1.16.dist-info/METADATA
pygridgain-9.1.16.dist-info/licenses/LICENSE
pygridgain-9.1.16.dist-info/licenses/NOTICE
pygridgain/end_point.py
pygridgain/async_node_connection.py
pygridgain/ssl_config.py
pygridgain/async_structures.py
pygridgain/constants.py
pygridgain/_native_extension.cpython-313-darwin.so
pygridgain/__init__.py
pygridgain/bitmask_feature.py
pygridgain/utils.py
pygridgain/protocol_context.py
pygridgain/async_client.py
pygridgain/ignite_error.py
pygridgain/async_binary_map.py
pygridgain/error_code.py
pygridgain/_version.txt
pygridgain/basic_authenticator.py
pygridgain/async_cluster_connection.py
