Metadata-Version: 2.4
Name: pygridgain
Version: 9.1.16
Summary: GridGain 9 Python Client
Author-email: GridGain Systems <eng@gridgain.com>
License-Expression: LicenseRef-GridGain-Systems-Proprietary
Project-URL: Homepage, https://www.gridgain.com
Project-URL: Documentation, https://www.gridgain.com/docs/gridgain9/latest/developers-guide/clients/overview
Keywords: gridgain,ignite,database,dbms,datagrid,sql
Classifier: Intended Audience :: Developers
Classifier: Topic :: Database :: Front-Ends
Classifier: Topic :: Software Development :: Libraries :: Python Modules
Classifier: Programming Language :: C++
Classifier: Programming Language :: Python
Classifier: Programming Language :: Python :: 3
Classifier: Programming Language :: Python :: 3.10
Classifier: Programming Language :: Python :: 3.11
Classifier: Programming Language :: Python :: 3.12
Classifier: Programming Language :: Python :: 3.13
Classifier: Programming Language :: Python :: 3.14
Classifier: Programming Language :: Python :: 3 :: Only
Classifier: Operating System :: MacOS
Classifier: Operating System :: Microsoft :: Windows
Classifier: Operating System :: POSIX :: Linux
Requires-Python: >=3.10
License-File: LICENSE
License-File: NOTICE
Provides-Extra: test
Requires-Dist: pytest==8.2.2; extra == "test"
Requires-Dist: pytest-asyncio==1.1.0; extra == "test"
Requires-Dist: psutil==5.8.0; extra == "test"
Requires-Dist: teamcity-messages==1.33; extra == "test"
Requires-Dist: msgpack==1.1.2; extra == "test"
Provides-Extra: format
Requires-Dist: black==24.2.0; extra == "format"
Requires-Dist: isort==5.13.2; extra == "format"
Requires-Dist: ruff==0.4.3; extra == "format"
Dynamic: license-file
